{
  "step": 84,
  "insect_id": "Ant",
  "timestamp": 1753377493.4180784,
  "performance_metrics": {
    "confidence": 0.0,
    "action_accuracy": 0.9116041849958348,
    "energy_efficiency": 0.9211861675783578,
    "learning_rate": 0.01,
    "memory_utilization": 0.6690879088421243
  },
  "behavioral_metrics": {
    "behavior_duration": 1.0,
    "behavior_success": false,
    "energy_cost": 0.01,
    "information_gain": 0.23321590635221323
  },
  "case_metrics": {
    "case_type": "INS",
    "case_effectiveness": 0.0,
    "case_transitions": 83,
    "case_appropriateness": 0.6798329746570368
  }
}