{
  "step": 52,
  "insect_id": "Honeybee",
  "timestamp": 1753377473.5220194,
  "event_type": "simulation_step",
  "case": "ACC",
  "behavioral_state": "idle",
  "position": [
    0.0,
    0.0,
    0.0
  ],
  "performance": {
    "confidence": 0.0,
    "action": "unknown",
    "total_actions": 105
  },
  "context": {
    "step": 52,
    "insect_id": "Honeybee",
    "timestamp": 1753377473.5163708,
    "case": "ACC",
    "behavioral_state": "idle",
    "position": [
      0.0,
      0.0,
      0.0
    ],
    "sensory_data": {
      "visual": [
        1.2443244707417858,
        2.199510812274723,
        -0.930391545645208,
        0.282742610413283,
        -0.5730059466289813,
        0.6623848352388292,
        0.08347811213137653,
        -0.7237808817074025,
        0.22648708018508235,
        1.6701747206152582
      ],
      "olfactory": [
        -0.6403383055150255,
        1.7543533701021057,
        -1.4686963409645581,
        1.2360109747042325,
        0.7633682613585949
      ],
      "pheromonal": [
        0.8470875279466386,
        2.214489880878711,
        1.1151735912567067
      ],
      "mechanosensory": [
        1.9789660919877423,
        0.9666947077960829,
        -0.540604014118477,
        -0.6820353217484231
      ]
    },
    "processed_data": {
      "action_selected": "observe",
      "confidence": 0.7,
      "action_parameters": {
        "focus": "sensory_input",
        "duration": 1.0
      },
      "total_actions": 105,
      "case_transformations": 50
    }
  },
  "metadata": {
    "simulation_step": 52,
    "insect_type": "Honeybee",
    "neural_activity_level": 0.5986617954295655
  }
}